{
    "Author": "Aniket Saini",
    "name": "FanCode Live Matches API",
    "Repository": "https://github.com/AniketSainiOp/AniXFancode",
    "Version": "2.0",
    "last_updated": "04:35:06 PM 03-08-2025",
    "total_matches": 40,
    "live_matches": 11,
    "upcoming_matches": 28,
    "matches": [
        {
            "category": "Cricket",
            "title": "Usa Women Under 19 Vs West Indies Women Under 19",
            "tournament": "USA Women U19 tour of West Indies, 2025",
            "match_id": 131673,
            "status": "LIVE",
            "streamingStatus": "STARTED",
            "startTime": "03 August 2025 07:30 PM",
            "startDate": "01 January 1970 05:30 AM",
            "image": "https://www.fancode.com/skillup-uploads/cms-media/USA-Women-U19-tour-of-West-India,-2025_match-card.jpg",
            "adfree_stream": "https://in-mc-fdlive.fancode.com/mumbai/131673_english_hls_97958ta-di_h264/index.m3u8",
            "dai_stream": "https://dai.google.com/linear/hls/event/3QU_o9_sT7y24k8ytT3uZQ/master.m3u8",
            "Author": "Aniket Saini",
            "Fetched_by": "AniXFetcher",
            "Processing_Time": "2025-08-03T16:35:06.725732"
        },
        {
            "category": "Cricket",
            "title": "Rugby Cc Vs Pirates",
            "tournament": "ECS Gibraltar, 2025",
            "match_id": 132831,
            "status": "LIVE",
            "streamingStatus": "COMPLETED",
            "startTime": "03 August 2025 08:15 PM",
            "startDate": "01 January 1970 05:30 AM",
            "image": "https://images.fancode.com/aig/match/v1/132831_CASACARDS_APP.png",
            "adfree_stream": null,
            "dai_stream": null,
            "Author": "Aniket Saini",
            "Fetched_by": "AniXFetcher",
            "Processing_Time": "2025-08-03T16:35:06.725751"
        },
        {
            "category": "Golf",
            "title": "Main Feed   Day 4",
            "tournament": "Wyndham Championship 2025",
            "match_id": 132216,
            "status": "LIVE",
            "streamingStatus": "STARTED",
            "startTime": "03 August 2025 05:15 PM",
            "startDate": "01 January 1970 05:30 AM",
            "image": "https://www.fancode.com/skillup-uploads/cms-media/Wyndham-Championship-old-match-card.png",
            "adfree_stream": "https://in-mc-fdlive.fancode.com/mumbai/132216_english_hls_18059ta-di_h264/index.m3u8",
            "dai_stream": "https://dai.google.com/linear/hls/event/LSSgYzuNS82rF1IY7Hz56Q/master.m3u8",
            "Author": "Aniket Saini",
            "Fetched_by": "AniXFetcher",
            "Processing_Time": "2025-08-03T16:35:06.725763"
        },
        {
            "category": "Golf",
            "title": "Marquee Group   Day 4",
            "tournament": "Wyndham Championship 2025",
            "match_id": 132217,
            "status": "LIVE",
            "streamingStatus": "STARTED",
            "startTime": "03 August 2025 05:30 PM",
            "startDate": "01 January 1970 05:30 AM",
            "image": "https://www.fancode.com/skillup-uploads/cms-media/Wyndham-Championship-old-match-card.png",
            "adfree_stream": "https://in-mc-fdlive.fancode.com/mumbai/132217_english_hls_11189ta-di_h264/index.m3u8",
            "dai_stream": "https://dai.google.com/linear/hls/event/9zxgNdnzS9KrN5znAZPxMA/master.m3u8",
            "Author": "Aniket Saini",
            "Fetched_by": "AniXFetcher",
            "Processing_Time": "2025-08-03T16:35:06.725773"
        },
        {
            "category": "Golf",
            "title": "Featured Holes   Day 4",
            "tournament": "Wyndham Championship 2025",
            "match_id": 132219,
            "status": "LIVE",
            "streamingStatus": "STARTED",
            "startTime": "03 August 2025 05:45 PM",
            "startDate": "01 January 1970 05:30 AM",
            "image": "https://www.fancode.com/skillup-uploads/cms-media/Wyndham-Championship-old-match-card.png",
            "adfree_stream": "https://in-mc-fdlive.fancode.com/mumbai/132219_english_hls_2990ta-di_h264/index.m3u8",
            "dai_stream": "https://dai.google.com/linear/hls/event/COQrw8u5T9S8dq4smJKz3g/master.m3u8",
            "Author": "Aniket Saini",
            "Fetched_by": "AniXFetcher",
            "Processing_Time": "2025-08-03T16:35:06.725783"
        },
        {
            "category": "Formula 1",
            "title": "Race",
            "tournament": "F1 LENOVO HUNGARIAN GRAND PRIX 2025",
            "match_id": 118450,
            "status": "LIVE",
            "streamingStatus": "STARTED",
            "startTime": "03 August 2025 06:30 PM",
            "startDate": "01 January 1970 05:30 AM",
            "image": "https://www.fancode.com/skillup-uploads/cms-media/F1_Hungarian-Grand-Prix_old.jpg",
            "adfree_stream": "https://d1sv7s55gxtley.cloudfront.net/out/v1/1b38579b52e74e798fdb39f652e7c5be/index.m3u8",
            "dai_stream": "Unavailable",
            "Author": "Aniket Saini",
            "Fetched_by": "AniXFetcher",
            "Processing_Time": "2025-08-03T16:35:06.725794"
        },
        {
            "category": "Formula 1",
            "title": "Race",
            "tournament": "F1 LENOVO HUNGARIAN GRAND PRIX 2025",
            "match_id": 118450,
            "status": "LIVE",
            "streamingStatus": "STARTED",
            "startTime": "03 August 2025 06:30 PM",
            "startDate": "01 January 1970 05:30 AM",
            "image": "https://www.fancode.com/skillup-uploads/cms-media/F1_Hungarian-Grand-Prix_old.jpg",
            "adfree_stream": "https://d1nrq922l1bgfk.cloudfront.net/out/v1/597bc31a88484b9e957b8917d20ba079/index.m3u8",
            "dai_stream": "Unavailable",
            "Author": "Aniket Saini",
            "Fetched_by": "AniXFetcher",
            "Processing_Time": "2025-08-03T16:35:06.725804"
        },
        {
            "category": "Formula 1",
            "title": "Race",
            "tournament": "F1 LENOVO HUNGARIAN GRAND PRIX 2025",
            "match_id": 118450,
            "status": "LIVE",
            "streamingStatus": "STARTED",
            "startTime": "03 August 2025 06:30 PM",
            "startDate": "01 January 1970 05:30 AM",
            "image": "https://www.fancode.com/skillup-uploads/cms-media/F1_Hungarian-Grand-Prix_old.jpg",
            "adfree_stream": "https://d1qiw7nhet8pjk.cloudfront.net/out/v1/3a5748556f2c4605bfa590852a46c587/index.m3u8",
            "dai_stream": "Unavailable",
            "Author": "Aniket Saini",
            "Fetched_by": "AniXFetcher",
            "Processing_Time": "2025-08-03T16:35:06.725814"
        },
        {
            "category": "Golf",
            "title": "Featured Group   Day 4",
            "tournament": "Wyndham Championship 2025",
            "match_id": 132218,
            "status": "LIVE",
            "streamingStatus": "STARTED",
            "startTime": "03 August 2025 06:45 PM",
            "startDate": "01 January 1970 05:30 AM",
            "image": "https://www.fancode.com/skillup-uploads/cms-media/Wyndham-Championship-old-match-card.png",
            "adfree_stream": "https://in-mc-fdlive.fancode.com/mumbai/132218_english_hls_11442ta-di_h264/index.m3u8",
            "dai_stream": "https://dai.google.com/linear/hls/event/6huptVGCQMez1xxZvML8dg/master.m3u8",
            "Author": "Aniket Saini",
            "Fetched_by": "AniXFetcher",
            "Processing_Time": "2025-08-03T16:35:06.725825"
        },
        {
            "category": "Cricket",
            "title": "New Delhi Tigers Vs Outer Delhi Warriors",
            "tournament": "Delhi Premier League, 2025",
            "match_id": 132466,
            "status": "LIVE",
            "streamingStatus": "STARTED",
            "startTime": "03 August 2025 07:00 PM",
            "startDate": "01 January 1970 05:30 AM",
            "image": "https://www.fancode.com/skillup-uploads/cms-media/132466_5521_ODW_NDT_fc-Web.jpg",
            "adfree_stream": "https://in-mc-fdlive.fancode.com/mumbai/132466_english_hls_21620ta-di_h264/index.m3u8",
            "dai_stream": "https://dai.google.com/linear/hls/event/Ri2dtpIYRM6S6LOLxM6iCA/master.m3u8",
            "Author": "Aniket Saini",
            "Fetched_by": "AniXFetcher",
            "Processing_Time": "2025-08-03T16:35:06.725835"
        },
        {
            "category": "Baseball",
            "title": "Boston Red Sox Vs Houston Astros",
            "tournament": "Major League Baseball, 2025",
            "match_id": 132839,
            "status": "LIVE",
            "streamingStatus": "STARTED",
            "startTime": "03 August 2025 09:05 PM",
            "startDate": "01 January 1970 05:30 AM",
            "image": "https://images.fancode.com/aig/match/v1/132839_CASACARDS_APP.png",
            "adfree_stream": "https://in-mc-fdlive.fancode.com/mumbai/132839_english_hls_53942ta-di_h264/index.m3u8",
            "dai_stream": "Unavailable",
            "Author": "Aniket Saini",
            "Fetched_by": "AniXFetcher",
            "Processing_Time": "2025-08-03T16:35:06.725845"
        },
        {
            "category": "Cricket",
            "title": "Tally Rangers Vs Cecc",
            "tournament": "KCC T20 Summer League, 2025",
            "match_id": 130018,
            "status": "NOT_STARTED",
            "streamingStatus": "NOT_STARTED",
            "startTime": "03 August 2025 11:00 PM",
            "startDate": "01 January 1970 05:30 AM",
            "image": "https://www.fancode.com/skillup-uploads/cms-media/KCC-T20-Summer-League_old_02.jpg",
            "adfree_stream": null,
            "dai_stream": null,
            "Author": "Aniket Saini",
            "Fetched_by": "AniXFetcher",
            "Processing_Time": "2025-08-03T16:35:06.725855"
        },
        {
            "category": "Cricket",
            "title": "Rugby Cc Vs Sloggers",
            "tournament": "ECS Gibraltar, 2025",
            "match_id": 132832,
            "status": "NOT_STARTED",
            "streamingStatus": "NOT_STARTED",
            "startTime": "03 August 2025 11:15 PM",
            "startDate": "01 January 1970 05:30 AM",
            "image": "https://images.fancode.com/aig/match/v1/132832_CASACARDS_APP.png",
            "adfree_stream": null,
            "dai_stream": null,
            "Author": "Aniket Saini",
            "Fetched_by": "AniXFetcher",
            "Processing_Time": "2025-08-03T16:35:06.725864"
        },
        {
            "category": "Football",
            "title": "Fc Porto Vs Atlético De Madrid",
            "tournament": "Club Friendlies 2025",
            "match_id": 132188,
            "status": "NOT_STARTED",
            "streamingStatus": "NOT_STARTED",
            "startTime": "03 August 2025 11:30 PM",
            "startDate": "01 January 1970 05:30 AM",
            "image": "https://www.fancode.com/skillup-uploads/cms-media/FC-Porto-VS-Atletico-de-Madrid_old.jpg",
            "adfree_stream": null,
            "dai_stream": null,
            "Author": "Aniket Saini",
            "Fetched_by": "AniXFetcher",
            "Processing_Time": "2025-08-03T16:35:06.725875"
        },
        {
            "category": "Cricket",
            "title": "Gauhati Town Club Vs Nabajyoti Club",
            "tournament": "GTC Spring T20 Cup, 2nd Edition, 2025",
            "match_id": 132401,
            "status": "NOT_STARTED",
            "streamingStatus": "NOT_STARTED",
            "startTime": "04 August 2025 09:00 AM",
            "startDate": "01 January 1970 05:30 AM",
            "image": "https://images.fancode.com/aig/match/v2/132401_CASACARDS_APP.png",
            "adfree_stream": null,
            "dai_stream": null,
            "Author": "Aniket Saini",
            "Fetched_by": "AniXFetcher",
            "Processing_Time": "2025-08-03T16:35:06.725885"
        },
        {
            "category": "Cricket",
            "title": "Hubli Tigers Women Vs Shivamogga Lioness Women",
            "tournament": "Maharani Trophy, 2025",
            "match_id": 132917,
            "status": "NOT_STARTED",
            "streamingStatus": "NOT_STARTED",
            "startTime": "04 August 2025 09:45 AM",
            "startDate": "01 January 1970 05:30 AM",
            "image": "https://www.fancode.com/skillup-uploads/cms-media/Maharani-Trophy,-2025_match-card.jpg",
            "adfree_stream": null,
            "dai_stream": null,
            "Author": "Aniket Saini",
            "Fetched_by": "AniXFetcher",
            "Processing_Time": "2025-08-03T16:35:06.725896"
        },
        {
            "category": "Cricket",
            "title": "91 Yards Club Vs City Cricket Club",
            "tournament": "GTC Spring T20 Cup, 2nd Edition, 2025",
            "match_id": 132402,
            "status": "NOT_STARTED",
            "streamingStatus": "NOT_STARTED",
            "startTime": "04 August 2025 01:15 PM",
            "startDate": "01 January 1970 05:30 AM",
            "image": "https://images.fancode.com/aig/match/v2/132402_CASACARDS_APP.png",
            "adfree_stream": null,
            "dai_stream": null,
            "Author": "Aniket Saini",
            "Fetched_by": "AniXFetcher",
            "Processing_Time": "2025-08-03T16:35:06.725905"
        },
        {
            "category": "Cricket",
            "title": "Mangaluru Dragons Women Vs Bengaluru Blasters Women",
            "tournament": "Maharani Trophy, 2025",
            "match_id": 132918,
            "status": "NOT_STARTED",
            "streamingStatus": "NOT_STARTED",
            "startTime": "04 August 2025 01:45 PM",
            "startDate": "01 January 1970 05:30 AM",
            "image": "https://www.fancode.com/skillup-uploads/cms-media/Maharani-Trophy,-2025_match-card.jpg",
            "adfree_stream": null,
            "dai_stream": null,
            "Author": "Aniket Saini",
            "Fetched_by": "AniXFetcher",
            "Processing_Time": "2025-08-03T16:35:06.725915"
        },
        {
            "category": "Cricket",
            "title": "Kreative Sports Xi Vs Guildford",
            "tournament": "ECS England, Wimbledon, 2025",
            "match_id": 132052,
            "status": "NOT_STARTED",
            "streamingStatus": "NOT_STARTED",
            "startTime": "04 August 2025 02:30 PM",
            "startDate": "01 January 1970 05:30 AM",
            "image": "https://www.fancode.com/skillup-uploads/cms-media/ECS-England,-Wimbledon,-2025-old-match-card-op-2.jpg",
            "adfree_stream": null,
            "dai_stream": null,
            "Author": "Aniket Saini",
            "Fetched_by": "AniXFetcher",
            "Processing_Time": "2025-08-03T16:35:06.725926"
        },
        {
            "category": "Cricket",
            "title": "Wimbledon Vs Guildford",
            "tournament": "ECS England, Wimbledon, 2025",
            "match_id": 132053,
            "status": "NOT_STARTED",
            "streamingStatus": "NOT_STARTED",
            "startTime": "04 August 2025 04:30 PM",
            "startDate": "01 January 1970 05:30 AM",
            "image": "https://www.fancode.com/skillup-uploads/cms-media/ECS-England,-Wimbledon,-2025-old-match-card.jpg",
            "adfree_stream": null,
            "dai_stream": null,
            "Author": "Aniket Saini",
            "Fetched_by": "AniXFetcher",
            "Processing_Time": "2025-08-03T16:35:06.725936"
        },
        {
            "category": "Football",
            "title": "Daegu Vs Barcelona",
            "tournament": "Club Friendlies 2025",
            "match_id": 129909,
            "status": "NOT_STARTED",
            "streamingStatus": "NOT_STARTED",
            "startTime": "04 August 2025 04:30 PM",
            "startDate": "01 January 1970 05:30 AM",
            "image": "https://www.fancode.com/skillup-uploads/cms-media/Football_Fallback_Old_match-card.jpg",
            "adfree_stream": null,
            "dai_stream": null,
            "Author": "Aniket Saini",
            "Fetched_by": "AniXFetcher",
            "Processing_Time": "2025-08-03T16:35:06.725946"
        },
        {
            "category": "Cricket",
            "title": "Kreative Sports Xi Vs Cfs Pinnacle Pro",
            "tournament": "ECS England, Wimbledon, 2025",
            "match_id": 132054,
            "status": "NOT_STARTED",
            "streamingStatus": "NOT_STARTED",
            "startTime": "04 August 2025 06:30 PM",
            "startDate": "01 January 1970 05:30 AM",
            "image": "https://www.fancode.com/skillup-uploads/cms-media/ECS-England,-Wimbledon,-2025-old-match-card-op-2.jpg",
            "adfree_stream": null,
            "dai_stream": null,
            "Author": "Aniket Saini",
            "Fetched_by": "AniXFetcher",
            "Processing_Time": "2025-08-03T16:35:06.725956"
        },
        {
            "category": "Golf",
            "title": "World Feed   Day 4",
            "tournament": "Wyndham Championship 2025",
            "match_id": 132215,
            "status": "NOT_STARTED",
            "streamingStatus": "NOT_STARTED",
            "startTime": "03 August 2025 10:30 PM",
            "startDate": "01 January 1970 05:30 AM",
            "image": "https://www.fancode.com/skillup-uploads/cms-media/Wyndham-Championship-old-match-card.png",
            "adfree_stream": null,
            "dai_stream": null,
            "Author": "Aniket Saini",
            "Fetched_by": "AniXFetcher",
            "Processing_Time": "2025-08-03T16:35:06.725965"
        },
        {
            "category": "Cricket",
            "title": "West Indies Vs Pakistan",
            "tournament": "Pakistan tour of West Indies, 2025",
            "match_id": 131404,
            "status": "NOT_STARTED",
            "streamingStatus": "NOT_STARTED",
            "startTime": "04 August 2025 05:30 AM",
            "startDate": "01 January 1970 05:30 AM",
            "image": "https://www.fancode.com/skillup-uploads/cms-media/Cricket_Fallback_Old_match-card.jpg",
            "adfree_stream": null,
            "dai_stream": null,
            "Author": "Aniket Saini",
            "Fetched_by": "AniXFetcher",
            "Processing_Time": "2025-08-03T16:35:06.725974"
        },
        {
            "category": "Cricket",
            "title": "Cfs Pinnacle Pro Vs Wimbledon",
            "tournament": "ECS England, Wimbledon, 2025",
            "match_id": 132055,
            "status": "NOT_STARTED",
            "streamingStatus": "NOT_STARTED",
            "startTime": "04 August 2025 08:45 PM",
            "startDate": "01 January 1970 05:30 AM",
            "image": "https://www.fancode.com/skillup-uploads/cms-media/ECS-England,-Wimbledon,-2025-old-match-card.jpg",
            "adfree_stream": null,
            "dai_stream": null,
            "Author": "Aniket Saini",
            "Fetched_by": "AniXFetcher",
            "Processing_Time": "2025-08-03T16:35:06.725982"
        },
        {
            "category": "Cricket",
            "title": "Phoenix Cricketers Vs Ace Krm Panthers",
            "tournament": "KCC T10 Summer League, 2025",
            "match_id": 132138,
            "status": "NOT_STARTED",
            "streamingStatus": "NOT_STARTED",
            "startTime": "04 August 2025 10:15 PM",
            "startDate": "01 January 1970 05:30 AM",
            "image": "https://www.fancode.com/skillup-uploads/cms-media/KCC-T10-Summer-League,-2025_match-card.jpg",
            "adfree_stream": null,
            "dai_stream": null,
            "Author": "Aniket Saini",
            "Fetched_by": "AniXFetcher",
            "Processing_Time": "2025-08-03T16:35:06.725991"
        },
        {
            "category": "Cricket",
            "title": "Kreative Sports Xi Vs Wimbledon",
            "tournament": "ECS England, Wimbledon, 2025",
            "match_id": 132056,
            "status": "NOT_STARTED",
            "streamingStatus": "NOT_STARTED",
            "startTime": "04 August 2025 10:45 PM",
            "startDate": "01 January 1970 05:30 AM",
            "image": "https://www.fancode.com/skillup-uploads/cms-media/ECS-England,-Wimbledon,-2025-old-match-card-op-2.jpg",
            "adfree_stream": null,
            "dai_stream": null,
            "Author": "Aniket Saini",
            "Fetched_by": "AniXFetcher",
            "Processing_Time": "2025-08-03T16:35:06.726000"
        },
        {
            "category": "Cricket",
            "title": "Bihar Cc Vs Bader & Nie Cricket Club",
            "tournament": "KCC T10 Summer League, 2025",
            "match_id": 132139,
            "status": "NOT_STARTED",
            "streamingStatus": "NOT_STARTED",
            "startTime": "05 August 2025 12:15 AM",
            "startDate": "01 January 1970 05:30 AM",
            "image": "https://www.fancode.com/skillup-uploads/cms-media/KCC-T10-Summer-League,-2025_match-card.jpg",
            "adfree_stream": null,
            "dai_stream": null,
            "Author": "Aniket Saini",
            "Fetched_by": "AniXFetcher",
            "Processing_Time": "2025-08-03T16:35:06.726010"
        },
        {
            "category": "Baseball",
            "title": "Chicago Cubs Vs Baltimore Orioles",
            "tournament": "Major League Baseball, 2025",
            "match_id": 132840,
            "status": "NOT_STARTED",
            "streamingStatus": "NOT_STARTED",
            "startTime": "03 August 2025 11:50 PM",
            "startDate": "01 January 1970 05:30 AM",
            "image": "https://images.fancode.com/aig/match/v1/132840_CASACARDS_APP.png",
            "adfree_stream": null,
            "dai_stream": null,
            "Author": "Aniket Saini",
            "Fetched_by": "AniXFetcher",
            "Processing_Time": "2025-08-03T16:35:06.726020"
        },
        {
            "category": "Baseball",
            "title": "Oakland Athletics Vs Arizona Diamondbacks",
            "tournament": "Major League Baseball, 2025",
            "match_id": 132841,
            "status": "NOT_STARTED",
            "streamingStatus": "NOT_STARTED",
            "startTime": "04 August 2025 01:35 AM",
            "startDate": "01 January 1970 05:30 AM",
            "image": "https://images.fancode.com/aig/match/v1/132841_CASACARDS_APP.png",
            "adfree_stream": null,
            "dai_stream": null,
            "Author": "Aniket Saini",
            "Fetched_by": "AniXFetcher",
            "Processing_Time": "2025-08-03T16:35:06.726030"
        },
        {
            "category": "Cricket",
            "title": "East Delhi Riders Vs West Delhi Lions",
            "tournament": "Delhi Premier League, 2025",
            "match_id": 132467,
            "status": "NOT_STARTED",
            "streamingStatus": "NOT_STARTED",
            "startTime": "04 August 2025 02:00 PM",
            "startDate": "01 January 1970 05:30 AM",
            "image": "https://www.fancode.com/skillup-uploads/cms-media/132467_5521_EDR_WDL_fc-Web.jpg",
            "adfree_stream": null,
            "dai_stream": null,
            "Author": "Aniket Saini",
            "Fetched_by": "AniXFetcher",
            "Processing_Time": "2025-08-03T16:35:06.726039"
        },
        {
            "category": "Cricket",
            "title": "Pakistan Champions Vs South Africa Champions",
            "tournament": "World Championship of Legends, 2025",
            "match_id": 129735,
            "status": "COMPLETED",
            "streamingStatus": "COMPLETED",
            "startTime": "02 August 2025 09:00 PM",
            "startDate": "01 January 1970 05:30 AM",
            "image": "https://www.fancode.com/skillup-uploads/cms-media/129726_5370_PNC_SAC_fc-Web.jpg",
            "adfree_stream": null,
            "dai_stream": null,
            "Author": "Aniket Saini",
            "Fetched_by": "AniXFetcher",
            "Processing_Time": "2025-08-03T16:35:06.726048"
        },
        {
            "category": "Cricket",
            "title": "Central Delhi Kings Vs New Delhi Tigers",
            "tournament": "Delhi Premier League, 2025",
            "match_id": 132468,
            "status": "NOT_STARTED",
            "streamingStatus": "NOT_STARTED",
            "startTime": "04 August 2025 07:00 PM",
            "startDate": "01 January 1970 05:30 AM",
            "image": "https://www.fancode.com/skillup-uploads/cms-media/132468_5521_CDK_NDT_fc-Web.jpg",
            "adfree_stream": null,
            "dai_stream": null,
            "Author": "Aniket Saini",
            "Fetched_by": "AniXFetcher",
            "Processing_Time": "2025-08-03T16:35:06.726058"
        },
        {
            "category": "Cricket",
            "title": "Johor Vs Malacca",
            "tournament": "MCA Men's T20 Inter-State Championship, 2025",
            "match_id": 132627,
            "status": "NOT_STARTED",
            "streamingStatus": "NOT_STARTED",
            "startTime": "05 August 2025 07:00 AM",
            "startDate": "01 January 1970 05:30 AM",
            "image": "https://www.fancode.com/skillup-uploads/cms-media/132627_5524_JOH_MEL_fc-web.jpg",
            "adfree_stream": null,
            "dai_stream": null,
            "Author": "Aniket Saini",
            "Fetched_by": "AniXFetcher",
            "Processing_Time": "2025-08-03T16:35:06.726068"
        },
        {
            "category": "Cricket",
            "title": "Kelantan Vs Pahang",
            "tournament": "MCA Men's T20 Inter-State Championship, 2025",
            "match_id": 132628,
            "status": "NOT_STARTED",
            "streamingStatus": "NOT_STARTED",
            "startTime": "05 August 2025 07:30 AM",
            "startDate": "01 January 1970 05:30 AM",
            "image": "https://www.fancode.com/skillup-uploads/cms-media/132628_5524_KEL_PHG_fc-web.jpg",
            "adfree_stream": null,
            "dai_stream": null,
            "Author": "Aniket Saini",
            "Fetched_by": "AniXFetcher",
            "Processing_Time": "2025-08-03T16:35:06.726078"
        },
        {
            "category": "Cricket",
            "title": "Bud Cricket Club Vs Guwahati Giants",
            "tournament": "GTC Spring T20 Cup, 2nd Edition, 2025",
            "match_id": 132403,
            "status": "NOT_STARTED",
            "streamingStatus": "NOT_STARTED",
            "startTime": "05 August 2025 09:00 AM",
            "startDate": "01 January 1970 05:30 AM",
            "image": "https://images.fancode.com/aig/match/v1/132403_CASACARDS_APP.png",
            "adfree_stream": null,
            "dai_stream": null,
            "Author": "Aniket Saini",
            "Fetched_by": "AniXFetcher",
            "Processing_Time": "2025-08-03T16:35:06.726087"
        },
        {
            "category": "Cricket",
            "title": "Mysore Warriors Women Vs Hubli Tigers Women",
            "tournament": "Maharani Trophy, 2025",
            "match_id": 132919,
            "status": "NOT_STARTED",
            "streamingStatus": "NOT_STARTED",
            "startTime": "05 August 2025 09:45 AM",
            "startDate": "01 January 1970 05:30 AM",
            "image": "https://www.fancode.com/skillup-uploads/cms-media/Maharani-Trophy,-2025_match-card.jpg",
            "adfree_stream": null,
            "dai_stream": null,
            "Author": "Aniket Saini",
            "Fetched_by": "AniXFetcher",
            "Processing_Time": "2025-08-03T16:35:06.726097"
        },
        {
            "category": "Cricket",
            "title": "Kuala Lumpur Vs Penang",
            "tournament": "MCA Men's T20 Inter-State Championship, 2025",
            "match_id": 132629,
            "status": "NOT_STARTED",
            "streamingStatus": "NOT_STARTED",
            "startTime": "05 August 2025 11:30 AM",
            "startDate": "01 January 1970 05:30 AM",
            "image": "https://www.fancode.com/skillup-uploads/cms-media/132629_5524_KL_PEN_fc-web.jpg",
            "adfree_stream": null,
            "dai_stream": null,
            "Author": "Aniket Saini",
            "Fetched_by": "AniXFetcher",
            "Processing_Time": "2025-08-03T16:35:06.726106"
        },
        {
            "category": "Cricket",
            "title": "Putrajaya Vs Sarawak",
            "tournament": "MCA Men's T20 Inter-State Championship, 2025",
            "match_id": 132630,
            "status": "NOT_STARTED",
            "streamingStatus": "NOT_STARTED",
            "startTime": "05 August 2025 12:00 PM",
            "startDate": "01 January 1970 05:30 AM",
            "image": "https://www.fancode.com/skillup-uploads/cms-media/132630_5524_PJY_SAR_fc-web.jpg",
            "adfree_stream": null,
            "dai_stream": null,
            "Author": "Aniket Saini",
            "Fetched_by": "AniXFetcher",
            "Processing_Time": "2025-08-03T16:35:06.726116"
        },
        {
            "category": "Baseball",
            "title": "Los Angeles Dodgers Vs St. Louis Cardinals",
            "tournament": "Major League Baseball, 2025",
            "match_id": 132842,
            "status": "NOT_STARTED",
            "streamingStatus": "NOT_STARTED",
            "startTime": "05 August 2025 07:40 AM",
            "startDate": "01 January 1970 05:30 AM",
            "image": "https://images.fancode.com/aig/match/v1/132842_CASACARDS_APP.png",
            "adfree_stream": null,
            "dai_stream": null,
            "Author": "Aniket Saini",
            "Fetched_by": "AniXFetcher",
            "Processing_Time": "2025-08-03T16:35:06.726125"
        }
    ],
    "status": "active"
}