{
    "Author": "Aniket Saini",
    "name": "FanCode Live Matches API",
    "Repository": "https://github.com/AniketSainiOp/AniXFancode",
    "Version": "2.0",
    "last_updated": "12:25:06 AM 22-08-2025",
    "total_matches": 39,
    "live_matches": 3,
    "upcoming_matches": 36,
    "matches": [
        {
            "category": "Cricket",
            "title": "India A Women Vs Australia A Women",
            "tournament": "India A Women tour of Australia, 2025",
            "match_id": 133235,
            "status": "LIVE",
            "streamingStatus": "STARTED",
            "startTime": "21 August 2025 04:30 AM",
            "startDate": "22 August 2025 04:30 AM",
            "image": "https://www.fancode.com/skillup-uploads/cms-media/IND_A_vs_AUS_Womens_Old_match-card-(2).jpg",
            "adfree_stream": "https://in-mc-pdlive.fancode.com/mumbai/133235_english_hls_ba3b3d673331519ta-di_h264/index.m3u8",
            "dai_stream": "https://dai.google.com/linear/hls/event/qtmPyhyZSiKn8sNg0R6rqw/master.m3u8",
            "Author": "Aniket Saini",
            "Fetched_by": "AniXFetcher",
            "Processing_Time": "2025-08-22T00:25:06.843402"
        },
        {
            "category": "Cricket",
            "title": "St Kitts And Nevis Patriots Vs Barbados Royals",
            "tournament": "Caribbean Premier League, 2025",
            "match_id": 132353,
            "status": "LIVE",
            "streamingStatus": "STARTED",
            "startTime": "22 August 2025 04:30 AM",
            "startDate": "01 January 1970 05:30 AM",
            "image": "https://www.fancode.com/skillup-uploads/cms-media/St-Kitts-and-Nevis-Patriots-VS-Barbados-Royals_old.jpg",
            "adfree_stream": "https://in-mc-fdlive.fancode.com/mumbai/132353_english_hls_679867d6f517491ta-di_h264/index.m3u8",
            "dai_stream": "https://dai.google.com/linear/hls/event/yRsEQ2v9Roy73aNIXtbBMw/master.m3u8",
            "Author": "Aniket Saini",
            "Fetched_by": "AniXFetcher",
            "Processing_Time": "2025-08-22T00:25:06.843418"
        },
        {
            "category": "Cricket",
            "title": "St Kitts And Nevis Patriots Vs Barbados Royals",
            "tournament": "Caribbean Premier League, 2025",
            "match_id": 132353,
            "status": "LIVE",
            "streamingStatus": "STARTED",
            "startTime": "22 August 2025 04:30 AM",
            "startDate": "01 January 1970 05:30 AM",
            "image": "https://www.fancode.com/skillup-uploads/cms-media/St-Kitts-and-Nevis-Patriots-VS-Barbados-Royals_old.jpg",
            "adfree_stream": "https://in-mc-fdlive.fancode.com/mumbai/132353_hindi_hls_dc3af41bb526502ta-di_h264/index.m3u8",
            "dai_stream": "https://dai.google.com/linear/hls/event/Yq8KrxaCSDiLPuEbN4PwdQ/master.m3u8",
            "Author": "Aniket Saini",
            "Fetched_by": "AniXFetcher",
            "Processing_Time": "2025-08-22T00:25:06.843430"
        },
        {
            "category": "Cricket",
            "title": "Alleppey Ripples Vs Thrissur Titans",
            "tournament": "Kerala Cricket League, 2025",
            "match_id": 133878,
            "status": "NOT_STARTED",
            "streamingStatus": "NOT_STARTED",
            "startTime": "22 August 2025 02:30 PM",
            "startDate": "01 January 1970 05:30 AM",
            "image": "https://www.fancode.com/skillup-uploads/cms-media/133878_5600_AP_TT_fc-Web_1755771731127.jpg",
            "adfree_stream": null,
            "dai_stream": null,
            "Author": "Aniket Saini",
            "Fetched_by": "AniXFetcher",
            "Processing_Time": "2025-08-22T00:25:06.843441"
        },
        {
            "category": "Cricket",
            "title": "Hubli Tigers Vs Gulbarga Mystics",
            "tournament": "Maharaja T20 Trophy, 2025",
            "match_id": 132807,
            "status": "NOT_STARTED",
            "streamingStatus": "NOT_STARTED",
            "startTime": "22 August 2025 03:15 PM",
            "startDate": "01 January 1970 05:30 AM",
            "image": "https://www.fancode.com/skillup-uploads/cms-media/132807_5530_HT_GMY_fc-Web_1755374792969.jpg",
            "adfree_stream": null,
            "dai_stream": null,
            "Author": "Aniket Saini",
            "Fetched_by": "AniXFetcher",
            "Processing_Time": "2025-08-22T00:25:06.843452"
        },
        {
            "category": "Cricket",
            "title": "Aries Kollam Sailors Vs Adani Trivandrum Royals",
            "tournament": "Kerala Cricket League, 2025",
            "match_id": 133879,
            "status": "NOT_STARTED",
            "streamingStatus": "NOT_STARTED",
            "startTime": "22 August 2025 06:45 PM",
            "startDate": "01 January 1970 05:30 AM",
            "image": "https://www.fancode.com/skillup-uploads/cms-media/133879_5600_AKS_TR_fc-Web_1755771731280.jpg",
            "adfree_stream": null,
            "dai_stream": null,
            "Author": "Aniket Saini",
            "Fetched_by": "AniXFetcher",
            "Processing_Time": "2025-08-22T00:25:06.843461"
        },
        {
            "category": "Cricket",
            "title": "New Delhi Tigers Vs Outer Delhi Warriors",
            "tournament": "Delhi Premier League, 2025",
            "match_id": 132493,
            "status": "NOT_STARTED",
            "streamingStatus": "NOT_STARTED",
            "startTime": "22 August 2025 07:00 PM",
            "startDate": "01 January 1970 05:30 AM",
            "image": "https://www.fancode.com/skillup-uploads/cms-media/132493_5521_NDT_ODW_fc-Web.jpg",
            "adfree_stream": null,
            "dai_stream": null,
            "Author": "Aniket Saini",
            "Fetched_by": "AniXFetcher",
            "Processing_Time": "2025-08-22T00:25:06.843471"
        },
        {
            "category": "Cricket",
            "title": "Shivamogga Lions Vs Mangaluru Dragons",
            "tournament": "Maharaja T20 Trophy, 2025",
            "match_id": 132808,
            "status": "NOT_STARTED",
            "streamingStatus": "NOT_STARTED",
            "startTime": "22 August 2025 07:15 PM",
            "startDate": "01 January 1970 05:30 AM",
            "image": "https://www.fancode.com/skillup-uploads/cms-media/132808_5530_SS_MD_fc-Web_1755374792933.jpg",
            "adfree_stream": null,
            "dai_stream": null,
            "Author": "Aniket Saini",
            "Fetched_by": "AniXFetcher",
            "Processing_Time": "2025-08-22T00:25:06.843481"
        },
        {
            "category": "Cricket",
            "title": "Birmingham Phoenix Women Vs Welsh Fire Women",
            "tournament": "The Hundred Women, 2025",
            "match_id": 132279,
            "status": "NOT_STARTED",
            "streamingStatus": "NOT_STARTED",
            "startTime": "22 August 2025 07:30 PM",
            "startDate": "01 January 1970 05:30 AM",
            "image": "https://www.fancode.com/skillup-uploads/cms-media/132279_5506_BPH-W_WEF-W_Fc-Web.jpg",
            "adfree_stream": null,
            "dai_stream": null,
            "Author": "Aniket Saini",
            "Fetched_by": "AniXFetcher",
            "Processing_Time": "2025-08-22T00:25:06.843492"
        },
        {
            "category": "Cricket",
            "title": "Birmingham Phoenix Vs Welsh Fire",
            "tournament": "The Hundred, 2025",
            "match_id": 132245,
            "status": "NOT_STARTED",
            "streamingStatus": "NOT_STARTED",
            "startTime": "22 August 2025 11:00 PM",
            "startDate": "01 January 1970 05:30 AM",
            "image": "https://www.fancode.com/skillup-uploads/cms-media/132245_5505_BPH_WEF_fc-web.jpg",
            "adfree_stream": null,
            "dai_stream": null,
            "Author": "Aniket Saini",
            "Fetched_by": "AniXFetcher",
            "Processing_Time": "2025-08-22T00:25:06.843505"
        },
        {
            "category": "Cricket",
            "title": "Melbourne Renegades Academy Vs Adelaide Strikers Academy",
            "tournament": "Top End T20 Series, 2025",
            "match_id": 133525,
            "status": "NOT_STARTED",
            "streamingStatus": "NOT_STARTED",
            "startTime": "22 August 2025 07:00 AM",
            "startDate": "01 January 1970 05:30 AM",
            "image": "https://www.fancode.com/skillup-uploads/cms-media/133525_5574_MRA_ASA_fc-web.jpg",
            "adfree_stream": null,
            "dai_stream": null,
            "Author": "Aniket Saini",
            "Fetched_by": "AniXFetcher",
            "Processing_Time": "2025-08-22T00:25:06.843515"
        },
        {
            "category": "Cricket",
            "title": "Northern Territory Strike Vs Perth Scorchers Academy",
            "tournament": "Top End T20 Series, 2025",
            "match_id": 133526,
            "status": "NOT_STARTED",
            "streamingStatus": "NOT_STARTED",
            "startTime": "22 August 2025 09:00 AM",
            "startDate": "01 January 1970 05:30 AM",
            "image": "https://www.fancode.com/skillup-uploads/cms-media/133526_5574_NTS_PSA_fc-web.jpg",
            "adfree_stream": null,
            "dai_stream": null,
            "Author": "Aniket Saini",
            "Fetched_by": "AniXFetcher",
            "Processing_Time": "2025-08-22T00:25:06.843524"
        },
        {
            "category": "Cricket",
            "title": "Romania Vs Czechia",
            "tournament": "ECN Romania-Czechia T20I, 2025",
            "match_id": 134941,
            "status": "NOT_STARTED",
            "streamingStatus": "NOT_STARTED",
            "startTime": "22 August 2025 12:00 PM",
            "startDate": "01 January 1970 05:30 AM",
            "image": "https://www.fancode.com/skillup-uploads/cms-media/ECN-Romania-Czechia-T20I,-2025_Match_card_1755759374155.jpg",
            "adfree_stream": null,
            "dai_stream": null,
            "Author": "Aniket Saini",
            "Fetched_by": "AniXFetcher",
            "Processing_Time": "2025-08-22T00:25:06.843534"
        },
        {
            "category": "Cricket",
            "title": "Renaissance Challengers Vs Yalla Shabab Giants",
            "tournament": "Oman D20 League, 2025",
            "match_id": 133684,
            "status": "NOT_STARTED",
            "streamingStatus": "NOT_STARTED",
            "startTime": "22 August 2025 12:30 PM",
            "startDate": "01 January 1970 05:30 AM",
            "image": "https://www.fancode.com/skillup-uploads/cms-media/133684_5590_RNC_YSG_fc-Web.jpg",
            "adfree_stream": null,
            "dai_stream": null,
            "Author": "Aniket Saini",
            "Fetched_by": "AniXFetcher",
            "Processing_Time": "2025-08-22T00:25:06.843544"
        },
        {
            "category": "Cricket",
            "title": "1.kieler Htc Vs Vfb Fallersleben",
            "tournament": "ECS Germany, Kiel, 2025",
            "match_id": 134146,
            "status": "NOT_STARTED",
            "streamingStatus": "NOT_STARTED",
            "startTime": "22 August 2025 12:45 PM",
            "startDate": "01 January 1970 05:30 AM",
            "image": "https://images.fancode.com/aig/match/v1/134146_CASACARDS_APP.png",
            "adfree_stream": null,
            "dai_stream": null,
            "Author": "Aniket Saini",
            "Fetched_by": "AniXFetcher",
            "Processing_Time": "2025-08-22T00:25:06.843554"
        },
        {
            "category": "Cricket",
            "title": "Toombul Vs Northern Suburbs",
            "tournament": "KFC T20 Max, 2025",
            "match_id": 134879,
            "status": "NOT_STARTED",
            "streamingStatus": "NOT_STARTED",
            "startTime": "22 August 2025 01:30 PM",
            "startDate": "01 January 1970 05:30 AM",
            "image": "https://www.fancode.com/skillup-uploads/cms-media/134879_5623_TMB_NSB_Fc-Web_1755807575971.jpg",
            "adfree_stream": null,
            "dai_stream": null,
            "Author": "Aniket Saini",
            "Fetched_by": "AniXFetcher",
            "Processing_Time": "2025-08-22T00:25:06.843564"
        },
        {
            "category": "Cricket",
            "title": "Austria Vs Belgium",
            "tournament": "ECI Austria-Belgium, 2025",
            "match_id": 135001,
            "status": "NOT_STARTED",
            "streamingStatus": "NOT_STARTED",
            "startTime": "22 August 2025 01:45 PM",
            "startDate": "01 January 1970 05:30 AM",
            "image": "https://www.fancode.com/skillup-uploads/cms-media/ECI-Austria-Belgium-2025_Old_match-card.jpg",
            "adfree_stream": null,
            "dai_stream": null,
            "Author": "Aniket Saini",
            "Fetched_by": "AniXFetcher",
            "Processing_Time": "2025-08-22T00:25:06.843574"
        },
        {
            "category": "Cricket",
            "title": "North Delhi Strikers Women Vs East Delhi Riders Women",
            "tournament": "Delhi Women's Premier League, 2025",
            "match_id": 132976,
            "status": "NOT_STARTED",
            "streamingStatus": "NOT_STARTED",
            "startTime": "22 August 2025 02:00 PM",
            "startDate": "01 January 1970 05:30 AM",
            "image": "https://www.fancode.com/skillup-uploads/cms-media/132976_5536_NDS-W_EDR-W_fc_web_1755513540618.jpg",
            "adfree_stream": null,
            "dai_stream": null,
            "Author": "Aniket Saini",
            "Fetched_by": "AniXFetcher",
            "Processing_Time": "2025-08-22T00:25:06.843585"
        },
        {
            "category": "Cricket",
            "title": "Ksv Kings Vs Sg Findorff",
            "tournament": "ECS Germany, Kiel, 2025",
            "match_id": 134147,
            "status": "NOT_STARTED",
            "streamingStatus": "NOT_STARTED",
            "startTime": "22 August 2025 02:45 PM",
            "startDate": "01 January 1970 05:30 AM",
            "image": "https://images.fancode.com/aig/match/v1/134147_CASACARDS_APP.png",
            "adfree_stream": null,
            "dai_stream": null,
            "Author": "Aniket Saini",
            "Fetched_by": "AniXFetcher",
            "Processing_Time": "2025-08-22T00:25:06.843594"
        },
        {
            "category": "Cricket",
            "title": "Pakistan Shaheens Vs Nepal",
            "tournament": "Top End T20 Series, 2025",
            "match_id": 133527,
            "status": "NOT_STARTED",
            "streamingStatus": "NOT_STARTED",
            "startTime": "22 August 2025 03:00 PM",
            "startDate": "01 January 1970 05:30 AM",
            "image": "https://www.fancode.com/skillup-uploads/cms-media/133527_5574_PKS_NEP_fc-web.jpg",
            "adfree_stream": null,
            "dai_stream": null,
            "Author": "Aniket Saini",
            "Fetched_by": "AniXFetcher",
            "Processing_Time": "2025-08-22T00:25:06.843604"
        },
        {
            "category": "Cricket",
            "title": "Papua New Guinea Vs Denmark",
            "tournament": "ICC CWC Challenge League A, 2024-26",
            "match_id": 133787,
            "status": "NOT_STARTED",
            "streamingStatus": "NOT_STARTED",
            "startTime": "22 August 2025 03:30 PM",
            "startDate": "01 January 1970 05:30 AM",
            "image": "https://www.fancode.com/skillup-uploads/cms-media/133787_4464_PNG_DEN_fc-Web.jpg",
            "adfree_stream": null,
            "dai_stream": null,
            "Author": "Aniket Saini",
            "Fetched_by": "AniXFetcher",
            "Processing_Time": "2025-08-22T00:25:06.843616"
        },
        {
            "category": "Cricket",
            "title": "Austria Vs Belgium",
            "tournament": "ECI Austria-Belgium, 2025",
            "match_id": 135002,
            "status": "NOT_STARTED",
            "streamingStatus": "NOT_STARTED",
            "startTime": "22 August 2025 03:45 PM",
            "startDate": "01 January 1970 05:30 AM",
            "image": "https://www.fancode.com/skillup-uploads/cms-media/ECI-Austria-Belgium-2025_Old_match-card.jpg",
            "adfree_stream": null,
            "dai_stream": null,
            "Author": "Aniket Saini",
            "Fetched_by": "AniXFetcher",
            "Processing_Time": "2025-08-22T00:25:06.843627"
        },
        {
            "category": "Cricket",
            "title": "Romania Vs Czechia",
            "tournament": "ECN Romania-Czechia T20I, 2025",
            "match_id": 134942,
            "status": "NOT_STARTED",
            "streamingStatus": "NOT_STARTED",
            "startTime": "22 August 2025 04:30 PM",
            "startDate": "01 January 1970 05:30 AM",
            "image": "https://www.fancode.com/skillup-uploads/cms-media/ECN-Romania-Czechia-T20I,-2025_Match_card_1755759374155.jpg",
            "adfree_stream": null,
            "dai_stream": null,
            "Author": "Aniket Saini",
            "Fetched_by": "AniXFetcher",
            "Processing_Time": "2025-08-22T00:25:06.843635"
        },
        {
            "category": "Cricket",
            "title": "Majees Titans Vs Muscat Thunders",
            "tournament": "Oman D20 League, 2025",
            "match_id": 133685,
            "status": "NOT_STARTED",
            "streamingStatus": "NOT_STARTED",
            "startTime": "22 August 2025 05:00 PM",
            "startDate": "01 January 1970 05:30 AM",
            "image": "https://www.fancode.com/skillup-uploads/cms-media/133685_5590_MAT_MUT_fc-Web.jpg",
            "adfree_stream": null,
            "dai_stream": null,
            "Author": "Aniket Saini",
            "Fetched_by": "AniXFetcher",
            "Processing_Time": "2025-08-22T00:25:06.843645"
        },
        {
            "category": "Cricket",
            "title": "Tbc Vs Tbc",
            "tournament": "ECS Germany, Kiel, 2025",
            "match_id": 134148,
            "status": "NOT_STARTED",
            "streamingStatus": "NOT_STARTED",
            "startTime": "22 August 2025 05:45 PM",
            "startDate": "01 January 1970 05:30 AM",
            "image": "https://www.fancode.com/skillup-uploads/cms-media/ECS-Germany,-Kiel,-2025_Match_card_.jpg",
            "adfree_stream": null,
            "dai_stream": null,
            "Author": "Aniket Saini",
            "Fetched_by": "AniXFetcher",
            "Processing_Time": "2025-08-22T00:25:06.843654"
        },
        {
            "category": "Cricket",
            "title": "Austria Vs Belgium",
            "tournament": "ECI Austria-Belgium, 2025",
            "match_id": 135003,
            "status": "NOT_STARTED",
            "streamingStatus": "NOT_STARTED",
            "startTime": "22 August 2025 06:15 PM",
            "startDate": "01 January 1970 05:30 AM",
            "image": "https://www.fancode.com/skillup-uploads/cms-media/ECI-Austria-Belgium-2025_Old_match-card.jpg",
            "adfree_stream": null,
            "dai_stream": null,
            "Author": "Aniket Saini",
            "Fetched_by": "AniXFetcher",
            "Processing_Time": "2025-08-22T00:25:06.843664"
        },
        {
            "category": "Cricket",
            "title": "Tbc Vs Tbc",
            "tournament": "Andhra Premier League, 2025",
            "match_id": 132783,
            "status": "NOT_STARTED",
            "streamingStatus": "NOT_STARTED",
            "startTime": "22 August 2025 06:30 PM",
            "startDate": "01 January 1970 05:30 AM",
            "image": "https://www.fancode.com/skillup-uploads/cms-media/Cricket_Fallback_Old_match-card.jpg",
            "adfree_stream": null,
            "dai_stream": null,
            "Author": "Aniket Saini",
            "Fetched_by": "AniXFetcher",
            "Processing_Time": "2025-08-22T00:25:06.843673"
        },
        {
            "category": "Cricket",
            "title": "Antigua & Barbuda Falcons Vs Guyana Amazon Warriors",
            "tournament": "Caribbean Premier League, 2025",
            "match_id": 132354,
            "status": "NOT_STARTED",
            "streamingStatus": "NOT_STARTED",
            "startTime": "23 August 2025 04:30 AM",
            "startDate": "01 January 1970 05:30 AM",
            "image": "https://www.fancode.com/skillup-uploads/cms-media/Antigua-Barbuda-Falcons-VS-Guyana-Amazon-Warriors_old.jpg",
            "adfree_stream": null,
            "dai_stream": null,
            "Author": "Aniket Saini",
            "Fetched_by": "AniXFetcher",
            "Processing_Time": "2025-08-22T00:25:06.843682"
        },
        {
            "category": "Cricket",
            "title": "Austria Vs Belgium",
            "tournament": "ECI Austria-Belgium, 2025",
            "match_id": 135004,
            "status": "NOT_STARTED",
            "streamingStatus": "NOT_STARTED",
            "startTime": "22 August 2025 08:15 PM",
            "startDate": "01 January 1970 05:30 AM",
            "image": "https://www.fancode.com/skillup-uploads/cms-media/ECI-Austria-Belgium-2025_Old_match-card.jpg",
            "adfree_stream": null,
            "dai_stream": null,
            "Author": "Aniket Saini",
            "Fetched_by": "AniXFetcher",
            "Processing_Time": "2025-08-22T00:25:06.843692"
        },
        {
            "category": "Cricket",
            "title": "Tbc Vs Tbc",
            "tournament": "ECS Germany, Kiel, 2025",
            "match_id": 134149,
            "status": "NOT_STARTED",
            "streamingStatus": "NOT_STARTED",
            "startTime": "22 August 2025 08:45 PM",
            "startDate": "01 January 1970 05:30 AM",
            "image": "https://www.fancode.com/skillup-uploads/cms-media/ECS-Germany,-Kiel,-2025_Match_card_.jpg",
            "adfree_stream": null,
            "dai_stream": null,
            "Author": "Aniket Saini",
            "Fetched_by": "AniXFetcher",
            "Processing_Time": "2025-08-22T00:25:06.843701"
        },
        {
            "category": "Cricket",
            "title": "Royal Oman Stallions Vs Ias Invincibles",
            "tournament": "Oman D20 League, 2025",
            "match_id": 133686,
            "status": "NOT_STARTED",
            "streamingStatus": "NOT_STARTED",
            "startTime": "22 August 2025 09:00 PM",
            "startDate": "01 January 1970 05:30 AM",
            "image": "https://www.fancode.com/skillup-uploads/cms-media/133686_5590_ROS_IAI_fc-Web.jpg",
            "adfree_stream": null,
            "dai_stream": null,
            "Author": "Aniket Saini",
            "Fetched_by": "AniXFetcher",
            "Processing_Time": "2025-08-22T00:25:06.843712"
        },
        {
            "category": "Football",
            "title": "Derby County Vs Bristol City",
            "tournament": "EFL Championship 2025-26",
            "match_id": 131996,
            "status": "NOT_STARTED",
            "streamingStatus": "NOT_STARTED",
            "startTime": "23 August 2025 12:30 AM",
            "startDate": "01 January 1970 05:30 AM",
            "image": "https://www.fancode.com/skillup-uploads/cms-media/131996_5489_DER_BRI_fc-web.jpg",
            "adfree_stream": null,
            "dai_stream": null,
            "Author": "Aniket Saini",
            "Fetched_by": "AniXFetcher",
            "Processing_Time": "2025-08-22T00:25:06.843722"
        },
        {
            "category": "Kabaddi",
            "title": "Amaravati Crushers Vs Vizianagaram Ninjas",
            "tournament": "Yuva Andhra Championship, 2025",
            "match_id": 133733,
            "status": "NOT_STARTED",
            "streamingStatus": "NOT_STARTED",
            "startTime": "22 August 2025 10:15 AM",
            "startDate": "01 January 1970 05:30 AM",
            "image": "https://www.fancode.com/skillup-uploads/cms-media/133733_5591_AC_VN_fc-Web.jpg",
            "adfree_stream": null,
            "dai_stream": null,
            "Author": "Aniket Saini",
            "Fetched_by": "AniXFetcher",
            "Processing_Time": "2025-08-22T00:25:06.843731"
        },
        {
            "category": "Kabaddi",
            "title": "Vizag Commandos Vs Bhimavaram Guardians",
            "tournament": "Yuva Andhra Championship, 2025",
            "match_id": 133734,
            "status": "NOT_STARTED",
            "streamingStatus": "NOT_STARTED",
            "startTime": "22 August 2025 11:45 AM",
            "startDate": "01 January 1970 05:30 AM",
            "image": "https://www.fancode.com/skillup-uploads/cms-media/133734_5591_VC_BG_fc-Web.jpg",
            "adfree_stream": null,
            "dai_stream": null,
            "Author": "Aniket Saini",
            "Fetched_by": "AniXFetcher",
            "Processing_Time": "2025-08-22T00:25:06.843741"
        },
        {
            "category": "Football",
            "title": "Real Betis Vs Alavés",
            "tournament": "LALIGA 2025-26",
            "match_id": 130846,
            "status": "NOT_STARTED",
            "streamingStatus": "NOT_STARTED",
            "startTime": "23 August 2025 01:00 AM",
            "startDate": "01 January 1970 05:30 AM",
            "image": "https://www.fancode.com/skillup-uploads/cms-media/Real-Betis-VS-Alaves_Old_match-card-(1).jpg",
            "adfree_stream": null,
            "dai_stream": null,
            "Author": "Aniket Saini",
            "Fetched_by": "AniXFetcher",
            "Processing_Time": "2025-08-22T00:25:06.843751"
        },
        {
            "category": "Football",
            "title": "Kashiwa Reysol Vs Urawa Red Diamonds",
            "tournament": "J League 2025",
            "match_id": 132083,
            "status": "NOT_STARTED",
            "streamingStatus": "NOT_STARTED",
            "startTime": "22 August 2025 03:30 PM",
            "startDate": "01 January 1970 05:30 AM",
            "image": "https://images.fancode.com/aig/match/v1/132083_CASACARDS_APP.png",
            "adfree_stream": null,
            "dai_stream": null,
            "Author": "Aniket Saini",
            "Fetched_by": "AniXFetcher",
            "Processing_Time": "2025-08-22T00:25:06.843761"
        },
        {
            "category": "Kabaddi",
            "title": "Krishna Defenders Vs Kakinada Kraken",
            "tournament": "Yuva Andhra Championship, 2025",
            "match_id": 133735,
            "status": "NOT_STARTED",
            "streamingStatus": "NOT_STARTED",
            "startTime": "22 August 2025 03:45 PM",
            "startDate": "01 January 1970 05:30 AM",
            "image": "https://www.fancode.com/skillup-uploads/cms-media/133735_5591_KD_KK_fc-Web.jpg",
            "adfree_stream": null,
            "dai_stream": null,
            "Author": "Aniket Saini",
            "Fetched_by": "AniXFetcher",
            "Processing_Time": "2025-08-22T00:25:06.843771"
        },
        {
            "category": "Kabaddi",
            "title": "Tirupati Raiders Vs Kurnool Knights",
            "tournament": "Yuva Andhra Championship, 2025",
            "match_id": 133736,
            "status": "NOT_STARTED",
            "streamingStatus": "NOT_STARTED",
            "startTime": "22 August 2025 05:30 PM",
            "startDate": "01 January 1970 05:30 AM",
            "image": "https://www.fancode.com/skillup-uploads/cms-media/133736_5591_TR_KKK_fc-Web.jpg",
            "adfree_stream": null,
            "dai_stream": null,
            "Author": "Aniket Saini",
            "Fetched_by": "AniXFetcher",
            "Processing_Time": "2025-08-22T00:25:06.843781"
        },
        {
            "category": "Football",
            "title": "Leganés Vs Cádiz",
            "tournament": "LALIGA Hypermotion 2025-26",
            "match_id": 134943,
            "status": "NOT_STARTED",
            "streamingStatus": "NOT_STARTED",
            "startTime": "23 August 2025 01:00 AM",
            "startDate": "01 January 1970 05:30 AM",
            "image": "https://www.fancode.com/skillup-uploads/cms-media/Football_Fallback_Old_match-card.jpg",
            "adfree_stream": null,
            "dai_stream": null,
            "Author": "Aniket Saini",
            "Fetched_by": "AniXFetcher",
            "Processing_Time": "2025-08-22T00:25:06.843790"
        }
    ],
    "status": "active"
}